ReVel/__init__.py
ReVel/test_revel.py
ReVel/LLEs/LLE.py
ReVel/LLEs/__init__.py
ReVel/LLEs/lime.py
ReVel/LLEs/random.py
ReVel/LLEs/shap.py
ReVel/classification/__init__.py
ReVel/classification/test.py
ReVel/classification/train.py
ReVel/load_data/CIFAR10.py
ReVel/load_data/CIFAR100.py
ReVel/load_data/EMNIST.py
ReVel/load_data/FGVC.py
ReVel/load_data/FashionMNIST.py
ReVel/load_data/Flowers.py
ReVel/load_data/Food101.py
ReVel/load_data/Imagenet.py
ReVel/load_data/OxfordIIITPet.py
ReVel/load_data/StandfordCars.py
ReVel/load_data/__init__.py
ReVel/perturbations/__init__.py
ReVel/perturbations/perturbation.py
ReVel/perturbations/quickshift.py
ReVel/perturbations/squares.py
ReVel/perturbations/utils.py
ReVel/revel/__init__.py
ReVel/revel/revel.py
revel_xai-1.0.3.dist-info/LICENSE
revel_xai-1.0.3.dist-info/METADATA
revel_xai-1.0.3.dist-info/WHEEL
revel_xai-1.0.3.dist-info/top_level.txt
revel_xai-1.0.3.dist-info/RECORD
